{"cameraMode":{"drawMode":0,"name":"Shaded","section":"Shading Mode"},"sceneLighting":true,"audioPlay":false,"sceneViewState":{"m_AlwaysRefresh":false,"showFog":true,"showSkybox":true,"showFlares":true,"showImageEffects":true,"showParticleSystems":true,"showVisualEffectGraphs":true,"m_FxEnabled":true},"in2DMode":false,"pivot":{"x":-13.60628890991211,"y":7.451942443847656,"z":-2.7083215713500978},"rotation":{"x":-0.08729910105466843,"y":0.8361241817474365,"z":-0.13949231803417207,"w":-0.5232754349708557},"size":17.550138473510743,"orthographic":false}