{"cameraMode":{"drawMode":0,"name":"Shaded","section":"Shading Mode"},"sceneLighting":true,"audioPlay":false,"sceneViewState":{"m_AlwaysRefresh":false,"showFog":true,"showSkybox":true,"showFlares":true,"showImageEffects":true,"showParticleSystems":true,"showVisualEffectGraphs":true,"m_FxEnabled":true},"in2DMode":false,"pivot":{"x":1621.5609130859375,"y":365.49298095703127,"z":-3873.7216796875},"rotation":{"x":0.12477836012840271,"y":-0.8287001848220825,"z":0.20438691973686219,"w":0.50592440366745},"size":187.43014526367188,"orthographic":false}